flask_storage/__init__.py
flask_storage/errors.py
flask_storage/files.py
flask_storage/images.py
flask_storage/mongo.py
flask_storage/signals.py
flask_storage/storage.py
flask_storage/views.py
flask_storage/backends/__init__.py
flask_storage/backends/local.py
flask_storage/backends/mock.py
flask_storage/backends/s3.py
flask_storage-1.4.3.dist-info/entry_points.txt
flask_storage-1.4.3.dist-info/licenses/LICENSE
flask_storage-1.4.3.dist-info/WHEEL
flask_storage-1.4.3.dist-info/METADATA
flask_storage-1.4.3.dist-info/RECORD
